arkham_utils/__init__.py
arkham_utils/arkhamdb/__init__.py
arkham_utils/arkhamdb/card.py
arkham_utils/arkhamdb/constants.py
arkham_utils/arkhamdb/public_deck.py
arkham_utils/arkhamdb/set.py
arkham_utils/card.py
arkham_utils/octgn/__init__.py
arkham_utils/octgn/card.py
arkham_utils/octgn/deck.py
arkham_utils/octgn/image_db.py
arkham_utils/octgn/set.py
arkham_utils/octgn/set_card.py
arkham_utils/pdf/__init__.py
arkham_utils/pdf/builder.py
arkham_utils/pdf/image_reader.py
arkham_utils/pdf/tiled_image_builder.py
arkham_utils-0.1.2.dist-info/METADATA
arkham_utils-0.1.2.dist-info/WHEEL
arkham_utils-0.1.2.dist-info/RECORD
