Metadata-Version: 2.1
Name: arkham-utils
Version: 0.1.2
Summary: Arkham Horror LCG utilities
Author: Ian Su
Author-email: iansu1979+github@gmail.com
Requires-Python: >=3.12,<4.0
Classifier: Programming Language :: Python :: 3
Classifier: Programming Language :: Python :: 3.12
Requires-Dist: Pillow (>=10.4.0,<11.0.0)
Requires-Dist: PyMuPDF (>=1.24.5,<2.0.0)
Requires-Dist: fpdf2 (>=2.7.4,<3.0.0)
Requires-Dist: platformdirs (>=4.3.7,<5.0.0)
Requires-Dist: requests (>=2.29.0,<3.0.0)
Requires-Dist: requests-cache (>=1.2.1,<2.0.0)
